storeErrorLogging/__init__.py
storeErrorLogging/storeErrorLogging.py
storeErrorLogging-0.2.10.dist-info/METADATA
storeErrorLogging-0.2.10.dist-info/WHEEL
storeErrorLogging-0.2.10.dist-info/top_level.txt
storeErrorLogging-0.2.10.dist-info/RECORD
