Metadata-Version: 2.2
Name: storeErrorLogging
Version: 0.2.10
Summary: # 🧩 SQL-Based Error & Print Logging for Flask
Home-page: https://github.com/brighamturner12/storeErrorLogging.git
Author: Brigham Turner
Author-email: brighamturner@narratebay.com
License: MIT
Project-URL: Documentation, https://github.com/brighamturner12/storeErrorLogging/blob/main/readme.md
Project-URL: Source Code, https://github.com/brighamturner12/storeErrorLogging/blob/main/simpleDescription.md
Classifier: Programming Language :: Python :: 3
Classifier: License :: OSI Approved :: MIT License
Classifier: Operating System :: OS Independent
Requires-Python: >=3.6
Requires-Dist: sqlalchemy
Requires-Dist: sqlalchemy
Requires-Dist: sqlalchemy
Requires-Dist: relativePathImport
Dynamic: author
Dynamic: author-email
Dynamic: classifier
Dynamic: description
Dynamic: description-content-type
Dynamic: home-page
Dynamic: license
Dynamic: project-url
Dynamic: requires-dist
Dynamic: requires-python
Dynamic: summary
